PSID/IPSID.py
PSID/LSSM.py
PSID/MatHelper.py
PSID/PSID.py
PSID/PrepModel.py
PSID/__init__.py
PSID/evaluation.py
PSID/example/IPSID_example.py
PSID/example/PSID_example.py
PSID/example/__init__.py
PSID/tests/test_PrepModel.py
psid-1.2.6.dist-info/licenses/LICENSE.md
psid-1.2.6.dist-info/METADATA
psid-1.2.6.dist-info/WHEEL
psid-1.2.6.dist-info/top_level.txt
psid-1.2.6.dist-info/RECORD
