Metadata-Version: 2.4
Name: PSID
Version: 1.2.6
Summary: Python implementation for preferential subspace identification (PSID)
Home-page: https://github.com/ShanechiLab/PyPSID
Author: Omid Sani
Author-email: Omid Sani <omidsani@gmail.com>
Classifier: Programming Language :: Python :: 3
Classifier: Operating System :: OS Independent
Requires-Python: >=3.6
License-File: LICENSE.md
Requires-Dist: numpy
Requires-Dist: scipy
Requires-Dist: scikit-learn
Requires-Dist: matplotlib
Requires-Dist: h5py
Dynamic: author
Dynamic: home-page
Dynamic: license-file
Dynamic: requires-python
